{
  "url": "https://www.olg.ca/en/lottery.html",
  "final_url": "https://www.olg.ca/en/lottery/top-games.html",
  "status": 200,
  "content_type": "text/html",
  "bytes": 477742,
  "elapsed_sec": 0.234,
  "fetched_at": "2025-09-14T02:08:56.621870Z",
  "sha256": "c6416366fc4e1fcb595ec9fe349ef7f80aeb322f0c8a31f1f6882d6451510e30",
  "headers": {
    "date": "Sun, 14 Sep 2025 02:08:56 GMT",
    "content-type": "text/html;charset=utf-8",
    "transfer-encoding": "chunked",
    "connection": "close",
    "content-encoding": "gzip",
    "cache-control": "max-age=1200",
    "expires": "Sun, 14 Sep 2025 02:10:59 GMT",
    "x-vhost": "publish",
    "x-content-type-options": "nosniff",
    "strict-transport-security": "max-age=31536000; includeSubDomains",
    "x-served-by": "cache-sjc1000094-SJC",
    "x-cache": "MISS",
    "x-timer": "S1757815559.158350,VS0,VS0,VE573",
    "vary": "Accept-Encoding",
    "last-modified": "Sun, 14 Sep 2025 02:05:59 GMT",
    "cf-cache-status": "HIT",
    "age": "177",
    "set-cookie": "__cf_bm=0J9K7AHutIFuOcU4FTBikyGiB8cDUFcKWvpB3YA6LeY-1757815736-1.0.1.1-HYpFLF60FoCVF.i59S_CpElme66jQmmZ8HnFz_BPQeg.DVLLSOwfUXICF2yyledL7fq8a00WA2u08IzvIkmL.d4Sky0nQUaCbSAT1opVOXU; path=/; expires=Sun, 14-Sep-25 02:38:56 GMT; domain=.www.olg.ca; HttpOnly; Secure; SameSite=None",
    "server": "cloudflare",
    "cf-ray": "97ec56e17bd72ab0-LAX",
    "alt-svc": "h3=\":443\"; ma=86400"
  },
  "user_agent": "Mozilla/5.0 (Windows NT 10.0; Win64; x64) AppleWebKit/537.36 (KHTML, like Gecko) Chrome/124.0 Safari/537.36"
}