{
  "url": "https://www.mdlottery.com/games/racetrax/winning-numbers/",
  "final_url": "https://www.mdlottery.com/games/racetrax/winning-numbers/",
  "status": 200,
  "content_type": "text/html",
  "bytes": 73640,
  "elapsed_sec": 0.216,
  "fetched_at": "2025-09-14T17:44:02.579588Z",
  "sha256": "981721ec9e0c606f307e16ea985c7986e835c9da97748d9d326c1cd575a01503",
  "headers": {
    "date": "Sun, 14 Sep 2025 17:44:02 GMT",
    "content-type": "text/html; charset=UTF-8",
    "transfer-encoding": "chunked",
    "connection": "close",
    "content-encoding": "gzip",
    "vary": "Accept-Encoding,Cookie",
    "link": "<https://www.mdlottery.com/?p=102813>; rel=shortlink",
    "x-powered-by": "WP Engine",
    "x-ua-compatible": "IE=edge,chrome=1",
    "x-cacheable": "SHORT",
    "cache-control": "max-age=600, must-revalidate",
    "x-cache": "HIT: 20",
    "x-cache-group": "normal",
    "permissions-policy": "geolocation=(), midi=(), sync-xhr=(), microphone=(), camera=(), magnetometer=(), gyroscope=(), fullscreen=(self), payment=()",
    "referrer-policy": "origin",
    "strict-transport-security": "max-age=315360000; includeSubDomains",
    "x-content-type-options": "nosniff",
    "x-frame-options": "SAMEORIGIN",
    "x-xss-protection": "1; mode=block",
    "cf-cache-status": "DYNAMIC",
    "set-cookie": "__cf_bm=29OUy9Fgkz4u7dokFHKrboozjdgUqsXMF2Tn5i0beNE-1757871842-1.0.1.1-.n1OahZ47GXqAWv0QHeUZTs9jmZ3X7NyLHMN6b9hfs1Kc9o3WUZkgYkLdqOgqtoUZUw1GtkUtkBNVwaY4oDPKiMNausYtLm7yMZGjPc3DtE; path=/; expires=Sun, 14-Sep-25 18:14:02 GMT; domain=.www.mdlottery.com; HttpOnly; Secure; SameSite=None",
    "server": "cloudflare",
    "cf-ray": "97f1b0a738bea0c6-LAX",
    "alt-svc": "h3=\":443\"; ma=86400"
  },
  "user_agent": "Mozilla/5.0 (X11; Linux x86_64) AppleWebKit/537.36 (KHTML, like Gecko) Chrome/123.0 Safari/537.36",
  "request_headers": {
    "User-Agent": "Mozilla/5.0 (X11; Linux x86_64) AppleWebKit/537.36 (KHTML, like Gecko) Chrome/123.0 Safari/537.36",
    "Accept": "text/html,application/xhtml+xml,application/xml;q=0.9,application/json;q=0.9,*/*;q=0.8",
    "Accept-Language": "en-US,en;q=0.9",
    "Accept-Encoding": "gzip, deflate",
    "Referer": "https://www.mdlottery.com/games/racetrax/winning-numbers/",
    "Connection": "close",
    "Cache-Control": "no-cache",
    "Pragma": "no-cache"
  }
}